migrations/__init__.py
pde_tracker-0.2.dist-info/METADATA
pde_tracker-0.2.dist-info/WHEEL
pde_tracker-0.2.dist-info/top_level.txt
pde_tracker-0.2.dist-info/RECORD
