Metadata-Version: 2.1
Name: pde-tracker
Version: 0.2
Requires-Dist: Django
Requires-Dist: djangorestframework
